mysql_mcp/__init__.py
mysql_mcp/server.py
mysql_mcp_zag-2.0.0.dist-info/METADATA
mysql_mcp_zag-2.0.0.dist-info/WHEEL
mysql_mcp_zag-2.0.0.dist-info/entry_points.txt
mysql_mcp_zag-2.0.0.dist-info/RECORD
