Metadata-Version: 2.4
Name: mysql-mcp-zag
Version: 2.0.0
Summary: A modern MySQL Model Context Protocol (MCP) server built with FastMCP
Project-URL: Homepage, https://github.com/Michaelzag/mysql-mcp-zag
Project-URL: Repository, https://github.com/Michaelzag/mysql-mcp-zag
Project-URL: Issues, https://github.com/Michaelzag/mysql-mcp-zag/issues
Project-URL: Documentation, https://github.com/Michaelzag/mysql-mcp-zag#readme
Author-email: Michael Zag <Michael@MichaelZag.com>
License: MIT
Keywords: ai,database,llm,mcp,mysql
Classifier: Development Status :: 4 - Beta
Classifier: Intended Audience :: Developers
Classifier: License :: OSI Approved :: MIT License
Classifier: Programming Language :: Python :: 3
Classifier: Programming Language :: Python :: 3.13
Classifier: Topic :: Database
Classifier: Topic :: Software Development :: Libraries :: Python Modules
Requires-Python: >=3.13
Requires-Dist: fastmcp<3,>=2.14
Requires-Dist: mysql-connector-python>=9.4.0
